mkdocs_sitemap_exclusion/__init__.py
mkdocs_sitemap_exclusion/plugin.py
mkdocs_sitemap_exclusion-0.0.1.dist-info/licenses/LICENSE
mkdocs_sitemap_exclusion-0.0.1.dist-info/METADATA
mkdocs_sitemap_exclusion-0.0.1.dist-info/WHEEL
mkdocs_sitemap_exclusion-0.0.1.dist-info/entry_points.txt
mkdocs_sitemap_exclusion-0.0.1.dist-info/top_level.txt
mkdocs_sitemap_exclusion-0.0.1.dist-info/RECORD
