Metadata-Version: 2.4
Name: mkdocs_sitemap_exclusion
Version: 0.0.1
Summary: A MkDocs plugin that removes URLs from the sitemap.xml
Author: Dmitriy Reztsov
Author-email: Dmitriy Reztsov <rezcov_d@mail.ru>
License-Expression: MIT
Project-URL: Homepage, https://github.com/DmitriyReztsov/mkdocs_sitemap_exclusion
Project-URL: Issues, https://github.com/DmitriyReztsov/mkdocs_sitemap_exclusion/issues
Classifier: Programming Language :: Python :: 3
Classifier: Operating System :: OS Independent
Requires-Python: >=3.9
License-File: LICENSE
Dynamic: author
Dynamic: license-file
